stacksearch/__init__.py
Stack_Search-1.0.1.dist-info/LICENSE.txt
Stack_Search-1.0.1.dist-info/METADATA
Stack_Search-1.0.1.dist-info/WHEEL
Stack_Search-1.0.1.dist-info/top_level.txt
Stack_Search-1.0.1.dist-info/RECORD
