Metadata-Version: 2.1
Name: Stack-Search
Version: 1.0.1
Summary: An advanced exception handler that searches your exception in Stack Overflow
Home-page: https://github.com/pypa/sampleproject
Author: Saran Goda
Author-email: godasaran@gmail.com
License: UNKNOWN
Platform: UNKNOWN
Classifier: Programming Language :: Python :: 3
Classifier: License :: OSI Approved :: MIT License
Classifier: Operating System :: OS Independent
